ookcatalog/__init__.py
ookcatalog/catalog.py
ookcatalog/commands.py
ookcatalog/db.py
ookcatalog/templates/home.html
ookcatalog/templates/layout.html
ookcatalog/templates/search.html
ookcatalog/templates/table.html
ookcatalog/translations/fr/LC_MESSAGES/messages.mo
ookcatalog/translations/fr/LC_MESSAGES/messages.po
ookcatalog-0.2.2.dist-info/entry_points.txt
ookcatalog-0.2.2.dist-info/WHEEL
ookcatalog-0.2.2.dist-info/METADATA
ookcatalog-0.2.2.dist-info/RECORD
