Metadata-Version: 2.1
Name: ookcatalog
Version: 0.2.2
Summary: Light and hassle-free PostgreSQL data catalog
Author-email: Moté <automates@petitmote.fr>
Requires-Python: >=3.8
Classifier: Programming Language :: Python :: 3
Classifier: License :: OSI Approved :: MIT License
Classifier: Operating System :: OS Independent
Requires-Dist: flask
Requires-Dist: psycopg[binary]
Requires-Dist: Flask-Babel
Project-URL: Homepage, https://github.com/PetitMote/OokCatalog
Project-URL: Issues, https://github.com/PetitMote/OokCatalog/issues
